minrecord/__init__.py
minrecord/base.py
minrecord/comparable.py
minrecord/comparator.py
minrecord/config.py
minrecord/functional.py
minrecord/generic.py
minrecord/manager.py
minrecord/py.typed
minrecord/testing.py
minrecord/utils/__init__.py
minrecord/utils/imports.py
minrecord/utils/value.py
minrecord/utils/fallback/__init__.py
minrecord/utils/fallback/objectory.py
minrecord-0.3.0.dist-info/METADATA
minrecord-0.3.0.dist-info/WHEEL
minrecord-0.3.0.dist-info/licenses/LICENSE
minrecord-0.3.0.dist-info/RECORD
