Metadata-Version: 2.4
Name: minrecord
Version: 0.3.0
Dynamic: Maintainer
Dynamic: Maintainer-email
Summary: Minimalist library to record values in a ML workflow
Project-URL: homepage, https://github.com/durandtibo/minrecord
Project-URL: repository, https://github.com/durandtibo/minrecord
Project-URL: documentation, https://durandtibo.github.io/minrecord/
Author-email: Thibaut Durand <durand.tibo+gh@gmail.com>
License-Expression: BSD-3-Clause
License-File: LICENSE
Keywords: machine learning,record
Classifier: Development Status :: 4 - Beta
Classifier: Intended Audience :: Developers
Classifier: Intended Audience :: Information Technology
Classifier: Intended Audience :: Science/Research
Classifier: License :: OSI Approved :: BSD License
Classifier: Operating System :: POSIX :: Linux
Classifier: Programming Language :: Python :: 3.10
Classifier: Programming Language :: Python :: 3.11
Classifier: Programming Language :: Python :: 3.12
Classifier: Programming Language :: Python :: 3.13
Classifier: Programming Language :: Python :: 3.14
Classifier: Topic :: Scientific/Engineering
Classifier: Topic :: Scientific/Engineering :: Artificial Intelligence
Classifier: Topic :: Software Development :: Libraries
Requires-Python: >=3.10
Requires-Dist: coola<2.0,>=1.0
Provides-Extra: all
Requires-Dist: objectory<1.0,>=0.3.0; extra == 'all'
Provides-Extra: objectory
Requires-Dist: objectory<1.0,>=0.3.0; extra == 'objectory'
